main_functions/__init__.py
main_functions/square.py
main_functions-0.0.3.dist-info/METADATA
main_functions-0.0.3.dist-info/WHEEL
main_functions-0.0.3.dist-info/top_level.txt
main_functions-0.0.3.dist-info/RECORD
