Metadata-Version: 2.1
Name: main-functions
Version: 0.0.3
Summary: Simple math function package
Author: Monkey D. Luffy
Author-email: whydoyou@need.it
Classifier: Programming Language :: Python :: 3
Classifier: License :: OSI Approved :: MIT License
Classifier: Operating System :: OS Independent
Requires-Python: >=3.6
